{"v":"4.8.0","meta":{"g":"LottieFiles AE 3.0.2","a":"","k":"","d":"","tc":""},"fr":25,"ip":0,"op":65,"w":570,"h":550,"nm":"tracking","ddd":0,"assets":[],"layers":[{"ddd":0,"ind":1,"ty":4,"nm":"path","sr":1,"ks":{"o":{"a":0,"k":100,"ix":11},"r":{"a":0,"k":0,"ix":10},"p":{"a":0,"k":[334.5,309.5,0],"ix":2},"a":{"a":0,"k":[0,0,0],"ix":1},"s":{"a":0,"k":[100,100,100],"ix":6}},"ao":0,"shapes":[{"ty":"gr","it":[{"ind":0,"ty":"sh","ix":1,"ks":{"a":0,"k":{"i":[[0,0],[0,0],[0,-37.555],[0,0],[-37.555,0],[0,0],[0,-25.681],[0,0],[25.681,0],[0,0],[0,-23.748],[0,0],[-23.748,0],[0,0],[0,-21.539],[0,0],[21.539,0],[0,0]],"o":[[0,0],[-37.555,0],[0,0],[0,37.555],[0,0],[25.681,0],[0,0],[0,25.681],[0,0],[-23.748,0],[0,0],[0,23.748],[0,0],[21.539,0],[0,0],[0,21.539],[0,0],[0,0]],"v":[[-28.5,-196.5],[-117.5,-196.5],[-185.5,-128.5],[-185.5,-128.5],[-117.5,-60.5],[75,-60.5],[121.5,-14],[121.5,-14],[75,32.5],[-37.5,32.5],[-80.5,75.5],[-80.5,75.5],[-37.5,118.5],[146.5,118.5],[185.5,157.5],[185.5,157.5],[146.5,196.5],[-180.5,196.5]],"c":false},"ix":2},"nm":"Path 1","mn":"ADBE Vector Shape - Group","hd":false},{"ty":"st","c":{"a":0,"k":[1,0.474509805441,0.337254911661,1],"ix":3},"o":{"a":0,"k":100,"ix":4},"w":{"a":0,"k":34,"ix":5},"lc":2,"lj":1,"ml":10,"bm":0,"nm":"Stroke 1","mn":"ADBE Vector Graphic - Stroke","hd":false},{"ty":"tr","p":{"a":0,"k":[0,0],"ix":2},"a":{"a":0,"k":[0,0],"ix":1},"s":{"a":0,"k":[100,100],"ix":3},"r":{"a":0,"k":0,"ix":6},"o":{"a":0,"k":100,"ix":7},"sk":{"a":0,"k":0,"ix":4},"sa":{"a":0,"k":0,"ix":5},"nm":"Transform"}],"nm":"Group 1","np":2,"cix":2,"bm":0,"ix":1,"mn":"ADBE Vector Group","hd":false},{"ty":"tm","s":{"a":1,"k":[{"i":{"x":[0.667],"y":[1]},"o":{"x":[0.333],"y":[0]},"t":7,"s":[0]},{"t":22,"s":[100]}],"ix":1},"e":{"a":1,"k":[{"i":{"x":[0.667],"y":[1]},"o":{"x":[0.333],"y":[0]},"t":42,"s":[0]},{"t":59,"s":[100]}],"ix":2},"o":{"a":0,"k":0,"ix":3},"m":1,"ix":2,"nm":"Trim Paths 1","mn":"ADBE Vector Filter - Trim","hd":false}],"ip":0,"op":65,"st":0,"bm":0},{"ddd":0,"ind":2,"ty":4,"nm":"box","sr":1,"ks":{"o":{"a":0,"k":100,"ix":11},"r":{"a":0,"k":0,"ix":10},"p":{"a":0,"k":[438.455,112.909,0],"ix":2},"a":{"a":0,"k":[438.455,112.909,0],"ix":1},"s":{"a":1,"k":[{"i":{"x":[0.667,0.667,0.667],"y":[1,1,1]},"o":{"x":[0.333,0.333,0.333],"y":[0,0,0]},"t":0,"s":[0,0,100]},{"i":{"x":[0.667,0.667,0.667],"y":[1,1,1]},"o":{"x":[0.333,0.333,0.333],"y":[0,0,0]},"t":7,"s":[110,110,100]},{"i":{"x":[0.667,0.667,0.667],"y":[1,1,1]},"o":{"x":[0.333,0.333,0.333],"y":[0,0,0]},"t":10,"s":[100,100,100]},{"i":{"x":[0.667,0.667,0.667],"y":[1,1,1]},"o":{"x":[0.333,0.333,0.333],"y":[0,0,0]},"t":37,"s":[100,100,100]},{"i":{"x":[0.667,0.667,0.667],"y":[1,1,1]},"o":{"x":[0.333,0.333,0.333],"y":[0,0,0]},"t":40,"s":[110,110,100]},{"t":45,"s":[0,0,100]}],"ix":6}},"ao":0,"shapes":[{"ty":"gr","it":[{"ind":0,"ty":"sh","ix":1,"ks":{"a":0,"k":{"i":[[0,0],[0,0],[-3.213,0.001],[-1.091,1.09],[0,0],[0,0],[-2.272,2.272],[0,1.542],[0,0]],"o":[[0,0],[0.001,3.213],[1.542,0],[0,0],[0,0],[2.272,2.272],[1.09,-1.091],[0,0],[0,0]],"v":[[-34.909,-46.545],[-34.909,40.728],[-29.09,46.545],[-24.977,44.841],[0,19.864],[24.977,44.841],[33.206,44.84],[34.909,40.728],[34.909,-46.545]],"c":true},"ix":2},"nm":"Path 1","mn":"ADBE Vector Shape - Group","hd":false},{"ty":"fl","c":{"a":0,"k":[0.956862747669,0.572549045086,0.152941182256,1],"ix":4},"o":{"a":0,"k":100,"ix":5},"r":1,"bm":0,"nm":"Fill 1","mn":"ADBE Vector Graphic - Fill","hd":false},{"ty":"tr","p":{"a":0,"k":[438.455,66.363],"ix":2},"a":{"a":0,"k":[0,0],"ix":1},"s":{"a":0,"k":[100,100],"ix":3},"r":{"a":0,"k":0,"ix":6},"o":{"a":0,"k":100,"ix":7},"sk":{"a":0,"k":0,"ix":4},"sa":{"a":0,"k":0,"ix":5},"nm":"Transform"}],"nm":"Group 1","np":2,"cix":2,"bm":0,"ix":1,"mn":"ADBE Vector Group","hd":false},{"ty":"gr","it":[{"ind":0,"ty":"sh","ix":1,"ks":{"a":0,"k":{"i":[[3.213,0],[0,0],[0,3.213],[-3.213,0],[0,0],[0,-3.213]],"o":[[0,0],[-3.213,0],[0,-3.213],[0,0],[3.213,0],[0,3.213]],"v":[[14.545,5.818],[-14.545,5.818],[-20.364,0],[-14.545,-5.818],[14.545,-5.818],[20.364,0]],"c":true},"ix":2},"nm":"Path 1","mn":"ADBE Vector Shape - Group","hd":false},{"ty":"fl","c":{"a":0,"k":[1,0.713725507259,0.333333343267,1],"ix":4},"o":{"a":0,"k":100,"ix":5},"r":1,"bm":0,"nm":"Fill 1","mn":"ADBE Vector Graphic - Fill","hd":false},{"ty":"tr","p":{"a":0,"k":[371.545,182.727],"ix":2},"a":{"a":0,"k":[0,0],"ix":1},"s":{"a":0,"k":[100,100],"ix":3},"r":{"a":0,"k":0,"ix":6},"o":{"a":0,"k":100,"ix":7},"sk":{"a":0,"k":0,"ix":4},"sa":{"a":0,"k":0,"ix":5},"nm":"Transform"}],"nm":"Group 2","np":2,"cix":2,"bm":0,"ix":2,"mn":"ADBE Vector Group","hd":false},{"ty":"gr","it":[{"ind":0,"ty":"sh","ix":1,"ks":{"a":0,"k":{"i":[[3.213,0],[0,0],[0,3.213],[-3.213,0],[0,0],[0,-3.213]],"o":[[0,0],[-3.213,0],[0,-3.213],[0,0],[3.213,0],[0,3.213]],"v":[[32,5.818],[-32,5.818],[-37.818,0],[-32,-5.818],[32,-5.818],[37.818,0]],"c":true},"ix":2},"nm":"Path 1","mn":"ADBE Vector Shape - Group","hd":false},{"ty":"fl","c":{"a":0,"k":[1,0.713725507259,0.333333343267,1],"ix":4},"o":{"a":0,"k":100,"ix":5},"r":1,"bm":0,"nm":"Fill 1","mn":"ADBE Vector Graphic - Fill","hd":false},{"ty":"tr","p":{"a":0,"k":[389,165.273],"ix":2},"a":{"a":0,"k":[0,0],"ix":1},"s":{"a":0,"k":[100,100],"ix":3},"r":{"a":0,"k":0,"ix":6},"o":{"a":0,"k":100,"ix":7},"sk":{"a":0,"k":0,"ix":4},"sa":{"a":0,"k":0,"ix":5},"nm":"Transform"}],"nm":"Group 3","np":2,"cix":2,"bm":0,"ix":3,"mn":"ADBE Vector Group","hd":false},{"ty":"gr","it":[{"ind":0,"ty":"sh","ix":1,"ks":{"a":0,"k":{"i":[[3.213,0],[0,0],[0,-3.213],[0,0],[-3.213,0],[0,0],[0,0]],"o":[[0,0],[-3.213,0],[0,0],[0,3.213],[0,0],[0,0],[0,-3.213]],"v":[[34.909,-29.091],[-34.909,-29.091],[-40.727,-23.273],[-40.727,23.273],[-34.909,29.091],[40.727,29.091],[40.727,-23.273]],"c":true},"ix":2},"nm":"Path 1","mn":"ADBE Vector Shape - Group","hd":false},{"ty":"fl","c":{"a":0,"k":[1,0.713725507259,0.333333343267,1],"ix":4},"o":{"a":0,"k":100,"ix":5},"r":1,"bm":0,"nm":"Fill 1","mn":"ADBE Vector Graphic - Fill","hd":false},{"ty":"tr","p":{"a":0,"k":[502.455,48.909],"ix":2},"a":{"a":0,"k":[0,0],"ix":1},"s":{"a":0,"k":[100,100],"ix":3},"r":{"a":0,"k":0,"ix":6},"o":{"a":0,"k":100,"ix":7},"sk":{"a":0,"k":0,"ix":4},"sa":{"a":0,"k":0,"ix":5},"nm":"Transform"}],"nm":"Group 4","np":2,"cix":2,"bm":0,"ix":4,"mn":"ADBE Vector Group","hd":false},{"ty":"gr","it":[{"ind":0,"ty":"sh","ix":1,"ks":{"a":0,"k":{"i":[[3.213,0],[0,0],[0,-3.213],[0,0],[0,0],[0,3.213],[0,0]],"o":[[0,0],[-3.213,0],[0,0],[0,0],[3.213,0],[0,0],[0,-3.213]],"v":[[34.909,-29.091],[-34.909,-29.091],[-40.727,-23.273],[-40.727,29.091],[34.909,29.091],[40.727,23.273],[40.727,-23.273]],"c":true},"ix":2},"nm":"Path 1","mn":"ADBE Vector Shape - Group","hd":false},{"ty":"fl","c":{"a":0,"k":[1,0.713725507259,0.333333343267,1],"ix":4},"o":{"a":0,"k":100,"ix":5},"r":1,"bm":0,"nm":"Fill 1","mn":"ADBE Vector Graphic - Fill","hd":false},{"ty":"tr","p":{"a":0,"k":[374.455,48.909],"ix":2},"a":{"a":0,"k":[0,0],"ix":1},"s":{"a":0,"k":[100,100],"ix":3},"r":{"a":0,"k":0,"ix":6},"o":{"a":0,"k":100,"ix":7},"sk":{"a":0,"k":0,"ix":4},"sa":{"a":0,"k":0,"ix":5},"nm":"Transform"}],"nm":"Group 5","np":2,"cix":2,"bm":0,"ix":5,"mn":"ADBE Vector Group","hd":false},{"ty":"gr","it":[{"ind":0,"ty":"sh","ix":1,"ks":{"a":0,"k":{"i":[[-3.213,0],[0,0],[0,-3.213],[0,0],[3.213,0],[0,0],[0,3.213],[0,0]],"o":[[0,0],[3.213,0],[0,0],[0,3.213],[0,0],[-3.213,0],[0,0],[0,-3.213]],"v":[[-98.909,-93.091],[98.909,-93.091],[104.727,-87.273],[104.727,87.273],[98.909,93.091],[-98.909,93.091],[-104.727,87.273],[-104.727,-87.273]],"c":true},"ix":2},"nm":"Path 1","mn":"ADBE Vector Shape - Group","hd":false},{"ty":"fl","c":{"a":0,"k":[0.988235294819,0.800000011921,0.592156887054,1],"ix":4},"o":{"a":0,"k":100,"ix":5},"r":1,"bm":0,"nm":"Fill 1","mn":"ADBE Vector Graphic - Fill","hd":false},{"ty":"tr","p":{"a":0,"k":[438.455,112.909],"ix":2},"a":{"a":0,"k":[0,0],"ix":1},"s":{"a":0,"k":[100,100],"ix":3},"r":{"a":0,"k":0,"ix":6},"o":{"a":0,"k":100,"ix":7},"sk":{"a":0,"k":0,"ix":4},"sa":{"a":0,"k":0,"ix":5},"nm":"Transform"}],"nm":"Group 6","np":2,"cix":2,"bm":0,"ix":6,"mn":"ADBE Vector Group","hd":false}],"ip":0,"op":65,"st":0,"bm":0},{"ddd":0,"ind":3,"ty":4,"nm":"location","sr":1,"ks":{"o":{"a":0,"k":100,"ix":11},"r":{"a":0,"k":0,"ix":10},"p":{"a":0,"k":[105.273,403.82,0],"ix":2},"a":{"a":0,"k":[105.273,403.82,0],"ix":1},"s":{"a":1,"k":[{"i":{"x":[0.667,0.667,0.667],"y":[1,1,1]},"o":{"x":[0.333,0.333,0.333],"y":[0,0,0]},"t":17,"s":[0,0,100]},{"i":{"x":[0.667,0.667,0.667],"y":[1,1,1]},"o":{"x":[0.333,0.333,0.333],"y":[0,0,0]},"t":24,"s":[110,110,100]},{"i":{"x":[0.667,0.667,0.667],"y":[1,1,1]},"o":{"x":[0.167,0.167,0.167],"y":[0,0,0]},"t":27,"s":[100,100,100]},{"i":{"x":[0.667,0.667,0.667],"y":[1,1,1]},"o":{"x":[0.333,0.333,0.333],"y":[0,0,0]},"t":55,"s":[100,100,100]},{"i":{"x":[0.667,0.667,0.667],"y":[1,1,1]},"o":{"x":[0.333,0.333,0.333],"y":[0,0,0]},"t":58,"s":[110,110,100]},{"t":63,"s":[0,0,100]}],"ix":6}},"ao":0,"shapes":[{"ty":"gr","it":[{"ind":0,"ty":"sh","ix":1,"ks":{"a":0,"k":{"i":[[-22.493,0],[0,-22.493],[22.493,0],[0,22.493]],"o":[[22.493,0],[0,22.493],[-22.493,0],[0,-22.493]],"v":[[0,-40.727],[40.727,0],[0,40.727],[-40.727,0]],"c":true},"ix":2},"nm":"Path 1","mn":"ADBE Vector Shape - Group","hd":false},{"ty":"fl","c":{"a":0,"k":[0.439215689898,0.713725507259,0.988235294819,1],"ix":4},"o":{"a":0,"k":100,"ix":5},"r":1,"bm":0,"nm":"Fill 1","mn":"ADBE Vector Graphic - Fill","hd":false},{"ty":"tr","p":{"a":0,"k":[105.273,368.909],"ix":2},"a":{"a":0,"k":[0,0],"ix":1},"s":{"a":0,"k":[100,100],"ix":3},"r":{"a":0,"k":0,"ix":6},"o":{"a":0,"k":100,"ix":7},"sk":{"a":0,"k":0,"ix":4},"sa":{"a":0,"k":0,"ix":5},"nm":"Transform"}],"nm":"Group 1","np":2,"cix":2,"bm":0,"ix":1,"mn":"ADBE Vector Group","hd":false},{"ty":"gr","it":[{"ind":0,"ty":"sh","ix":1,"ks":{"a":0,"k":{"i":[[13.911,27.573],[28.28,2.089],[4.156,-0.284],[12.406,-25.499],[-16.468,-26.127],[0,0],[-2.71,1.727],[-0.456,0.716],[0,0]],"o":[[-12.406,-25.499],[-4.156,-0.284],[-28.28,2.089],[-13.911,27.573],[0,0],[1.727,2.71],[0.716,-0.456],[0,0],[16.468,-26.127]],"v":[[71.96,-71.587],[6.242,-116.15],[-6.242,-116.15],[-71.96,-71.587],[-67.84,14.961],[-4.906,113.671],[3.127,115.451],[4.906,113.671],[67.84,14.961]],"c":true},"ix":2},"nm":"Path 1","mn":"ADBE Vector Shape - Group","hd":false},{"ty":"fl","c":{"a":0,"k":[0.701960802078,0.847058832645,0.956862747669,1],"ix":4},"o":{"a":0,"k":100,"ix":5},"r":1,"bm":0,"nm":"Fill 1","mn":"ADBE Vector Graphic - Fill","hd":false},{"ty":"tr","p":{"a":0,"k":[105.273,403.82],"ix":2},"a":{"a":0,"k":[0,0],"ix":1},"s":{"a":0,"k":[100,100],"ix":3},"r":{"a":0,"k":0,"ix":6},"o":{"a":0,"k":100,"ix":7},"sk":{"a":0,"k":0,"ix":4},"sa":{"a":0,"k":0,"ix":5},"nm":"Transform"}],"nm":"Group 2","np":2,"cix":2,"bm":0,"ix":2,"mn":"ADBE Vector Group","hd":false}],"ip":0,"op":65,"st":0,"bm":0}],"markers":[]}